{"ANU": {"name": "Bruce Birch", "link": "https://researchers.anu.edu.au/researchers/birch-b", "colleges": "College of Asia & the Pacific", "email": "", "phone": "", "expertise": [], "interest": [], "biography": "", "project": [], "publication": []}, "Microsoft-Academic": [{"title": "iwaidja jurtbirrk songs bringing language and music together", "year": 2007, "source": "australian aboriginal studies", "authors": [{"name": "linda barwick"}, {"name": "bruce birch"}, {"name": "nicholas evans"}], "id": 8537395}, {"title": "notes on the contemporary knowledge of traditional material culture among the iwaidja cobourg peninsula arnhem land northern territory 2005 2006", "year": 2014, "source": "transactions of the royal society of south australia", "authors": [{"name": "kim akerman"}, {"name": "bruce birch"}, {"name": "nicholas evans"}], "id": 22421200}, {"title": "getting in line an investigation of spatial frames of reference in iwaidja", "year": 2011, "source": "", "authors": [{"name": "bruce birch", "affiliation": "australian national university"}, {"name": "cris edmondswathen", "affiliation": "rmit university"}]}, {"title": "the ma project crowdsourcing software for language documentation", "year": 2013, "source": "", "authors": [{"name": "bruce birch"}]}, {"title": "syllable reduction and deletion a reliable diagnostic for metrical structure in iwaidja", "year": 2011, "source": "", "authors": [{"name": "bruce birch"}]}, {"title": "the american clever man marrkijbu burdan merika", "year": 2011, "source": "", "authors": [{"name": "bruce birch"}]}, {"title": "marrwakani songs at lurrwik mary yamirr s outstation", "year": 2004, "source": "", "authors": [{"name": "bruce birch"}, {"name": "linda"}, {"name": "archie"}, {"name": "ronnie"}, {"name": "sam"}]}, {"title": "jurtbirrk love songs at australia day beach barbecue minjilang", "year": 2004, "source": "", "authors": [{"name": "cookie"}, {"name": "reggie"}, {"name": "reuben"}, {"name": "jimmy"}, {"name": "ronnie"}, {"name": "bruce birch"}]}, {"title": "locusts and dreams", "year": 2005, "source": "", "authors": [{"name": "bruce birch"}]}, {"title": "yanajanak and kalajbari songs", "year": 2004, "source": "", "authors": [{"name": "bruce birch"}, {"name": "archie"}, {"name": "yambikbik"}, {"name": "charlie mangulda"}]}], "ANDS-Grants": []}