{"ANU": {"name": "Christopher Ballard", "link": "https://researchers.anu.edu.au/researchers/ballard-chl", "colleges": "College of Asia & the Pacific", "email": "", "phone": "", "expertise": [], "interest": [], "biography": "", "project": [], "publication": []}, "Microsoft-Academic": [{"title": "resource wars the anthropology of mining", "year": 2003, "source": "annual review of anthropology", "authors": [{"name": "christopher ballard", "affiliation": "australian national university"}, {"name": "glenn banks", "affiliation": "australian defence force academy"}], "id": 195167216}, {"title": "the return of the past on drawing and dialogic history", "year": 2013, "source": "asia pacific journal of anthropology", "authors": [{"name": "christopher ballard"}], "id": 191816521}, {"title": "the end of the beginning mining sacred geographies memory and performance in lihir", "year": 2012, "source": "the australian journal of anthropology", "authors": [{"name": "nicholas a bainton", "affiliation": "university of queensland"}, {"name": "christopher ballard", "affiliation": "australian national university"}, {"name": "kirsty gillespie", "affiliation": "university of queensland"}], "id": 202606351}, {"title": "disks in the arches cluster survival in a starburst environment", "year": 2010, "source": "the astrophysical journal", "authors": [{"name": "andrea stolte", "affiliation": "university of california los angeles"}, {"name": "andrea stolte", "affiliation": "university of cologne"}, {"name": "m morris", "affiliation": "university of california los angeles"}, {"name": "a m ghez", "affiliation": "university of california los angeles"}, {"name": "tuan do", "affiliation": "university of california los angeles"}, {"name": "jessica r lu", "affiliation": "california institute of technology"}, {"name": "shelley a wright", "affiliation": "university of california berkeley"}, {"name": "christopher ballard"}, {"name": "elizabeth mills", "affiliation": "university of california los angeles"}, {"name": "keith matthews", "affiliation": "california institute of technology"}], "id": 1980519}, {"title": "disks in the arches cluster survival in a starburst environment", "year": 2010, "source": "arxiv solar and stellar astrophysics", "authors": [{"name": "andrea stolte", "affiliation": "university of california los angeles"}, {"name": "andrea stolte", "affiliation": "university of cologne"}, {"name": "m morris", "affiliation": "university of california los angeles"}, {"name": "a m ghez", "affiliation": "university of california los angeles"}, {"name": "tuan do", "affiliation": "university of california los angeles"}, {"name": "jessica r lu", "affiliation": "california institute of technology"}, {"name": "shelley a wright", "affiliation": "university of california berkeley"}, {"name": "christopher ballard"}, {"name": "elizabeth mills", "affiliation": "university of california los angeles"}, {"name": "keith matthews", "affiliation": "california institute of technology"}], "id": 2596918514}, {"title": "the sweet potato in oceania a reappraisal", "year": 2005, "source": "", "authors": [{"name": "christopher ballard", "affiliation": "university of pittsburgh"}, {"name": "paula brown", "affiliation": "verizon communications"}, {"name": "mike bourke"}, {"name": "tracy harwood"}]}, {"title": "stepping stones across the lihir islands developing cultural heritage management in the context of a gold mining operation", "year": 2011, "source": "international journal of cultural property", "authors": [{"name": "nicholas a bainton", "affiliation": "university of queensland"}, {"name": "christopher ballard", "affiliation": "australian national university"}, {"name": "kirsty gillespie", "affiliation": "university of queensland"}, {"name": "nicholas hall"}], "id": 35662283}, {"title": "the ok tedi settlement issues outcomes and implications", "year": 1999, "source": "pacific affairs", "authors": [{"name": "glenn banks"}, {"name": "christopher ballard"}], "id": 22496335}, {"title": "monitoring the environmental impact of mining in remote locations through remotely sensed data", "year": 2006, "source": "geocarto international", "authors": [{"name": "david paull", "affiliation": "university of new south wales"}, {"name": "glenn banks", "affiliation": "university of new south wales"}, {"name": "christopher ballard", "affiliation": "australian national university"}, {"name": "david gillieson", "affiliation": "james cook university"}], "id": 106004775}, {"title": "the ship as symbol in the prehistory of scandinavia and southeast asia", "year": 2004, "source": "world archaeology", "authors": [{"name": "christopher ballard"}, {"name": "richard bradley", "affiliation": "university of reading"}, {"name": "lise nordenborg myhre", "affiliation": "university of stavanger"}, {"name": "meredith wilson"}], "id": 14980801}], "ANDS-Grants": []}