{"ANU": {"name": "Christine Charles", "link": "https://researchers.anu.edu.au/researchers/charles-c", "colleges": "College of Science", "email": "christine.charles@anu.edu.au", "phone": "", "expertise": ["Plasma Physics Fusion Plasmas Electrical Discharges", "Aerospace Engineering", "Astronomical And Space Sciences", "Nanofabrication Growth And Self Assembly", "Physical Chemistry Of Materials", "Engineering Instrumentation", "Theory And Design Of Materials", "Electrical And Electronic Engineering"], "interest": ["My main research interest has been the investigation of the fundamental processes leading to ion acceleration in plasma systems both in the laboratory and in astrophysics, and the investigation of the numerous applied components that can be derived from it:Development of the Pocket Rocket propulsion module for CubeSats nano-satellitesPlasma thrusters and interplanetary space travel (inventor of the Helicon Double Layer Thruster)AU03 QB50 CubeSat space mission (Launch from International Space Station in March 2017)Development of plasma jets for biological aplications (wound healing)Nano-structure materials for hydrogen fuel cells (A French-Australian collaboration with the University of Orl\u00e9ans)Development of plasma models and plasma sources for applications to the microelectronics industry (etching, deposition, sputtering of materials) and\u00a0the emerging field of bio-materials (plasma polymers)Hydrogen-free optical waveguides for photonics (plasma deposition of silicon dioxide)"], "biography": "", "project": [], "publication": [{"title": "Naphthalene as a cubesat cold gas thruster propellant", "year": "2020", "source": "Frontiers in Physics, vol. 8, no. 389, pp. 1-8", "authors": ["Tsifakis D", "Christine Charles", "Boswell R"]}, {"title": "The INSPIRE-2 CubeSat for the QB50 Project", "year": "2020", "source": "Space Science Reviews, vol. 216, no. 40, pp. 1-31", "authors": ["Cairns I", "Christine Charles", "Dempster A"]}, {"title": "n Inductively-Coupled Plasma Electrothermal Radiofrequency Thruster", "year": "2020", "source": "Frontiers in Physics, vol. 8, no. 34, pp. 1-10", "authors": ["Tsifakis D", "Christine Charles", "Boswell R"]}, {"title": "Characterization and Control of an Ion-Acoustic Plasma Instability Downstream of a Diverging Magnetic Nozzle", "year": "2020", "source": "Frontiers in Physics, vol. 8, no. 24, pp. 1-11", "authors": ["Doyle S", "Bennet A", "Tsifakis D", "Christine Charles"]}, {"title": "High-temperature hypersonic Laval nozzle for non-LTE cavity ringdown spectroscopy", "year": "2020", "source": "Journal of Chemical Physics, vol. 152, no. 13, pp. 1-13", "authors": ["Dudas E", "Suas-David N", "Brahmachary S", "Christine Charles"]}, {"title": "Thermodynamic Analogy for Electrons Interacting with a Magnetic Nozzle", "year": "2020", "source": "Physical Review Letters, vol. 125, no. 16, pp. 1-5", "authors": ["Takahashi K", "Christine Charles", "Boswell R"]}, {"title": "Commentary: On helicon thrusters: Will they ever fly?", "year": "2020", "source": "Frontiers in Physics, vol. 8, no. 277, pp. 1-3", "authors": ["Takahashi K", "Christine Charles", "Boswell R"]}, {"title": "Decoupling ion energy and flux in intermediate pressure capacitively coupled plasmas via tailored voltage waveforms", "year": "2020", "source": "Plasma Sources Science and Technology, vol. 29, no. 12", "authors": ["Doyle S", "Gibson A", "Boswell R", "Christine Charles"]}, {"title": "Control of electron, ion and neutral heating in a radio-frequency electrothermal microthruster via dual-frequency voltage waveforms", "year": "2019", "source": "Plasma Sources Science and Technology, vol. 28, no. 3, pp. 1-15", "authors": ["Doyle S", "Gibson A", "Boswell R", "Christine Charles"]}, {"title": "Inducing locally structured ion energy distributions in intermediate-pressure plasmas", "year": "2019", "source": "Physics of Plasmas, vol. 26, no. 7", "authors": ["Doyle S", "Gibson A", "Boswell R", "Christine Charles"]}, {"title": "Field-aligned Boltzmann electric triple layer in a low-pressure expanding plasma", "year": "2019", "source": "Plasma Sources Science and Technology, vol. 28, no. 6, pp. 1-5", "authors": ["Bennet A", "Christine Charles", "Boswell R"]}, {"title": "Non-local plasma generation in a magnetic nozzle", "year": "2019", "source": "Physics of Plasmas, vol. 26, no. 7, pp. 1-9", "authors": ["Bennet A", "Christine Charles", "Boswell R"]}, {"title": "Current-Free Electric Double Layer in a Small Collisional Plasma Thruster Nozzle Simulation", "year": "2019", "source": "Frontiers in Physics, vol. 7, no. 200, pp. 1-8", "authors": ["Ho T", "Christine Charles", "Boswell R"]}, {"title": "Space micropropulsion systems for Cubesats and small satellites: From proximate targets to furthermost frontiers", "year": "2018", "source": "Applied Physics Reviews, vol. 5, no. 1, pp. 1-36pp", "authors": ["Levchenko I", "Bazaka K", "Ding Y", "Christine Charles"]}, {"title": "diabatic Expansion of Electron Gas in a Magnetic Nozzle", "year": "2018", "source": "Physical Review Letters, vol. 120, no. 4, pp. 5pp", "authors": ["Takahashi K", "Christine Charles", "Boswell R"]}, {"title": "In situ electrostatic characterisation of ion beams in the region of ion acceleration", "year": "2018", "source": "Physics of Plasmas, vol. 25, no. 2, pp. 1-8", "authors": ["Bennet A", "Christine Charles", "Boswell R"]}, {"title": "Performance modelling of plasma microthruster nozzles in vacuum", "year": "2018", "source": "Journal of Applied Physics, vol. 123, no. 17, pp. 1-15", "authors": ["Ho T", "Christine Charles", "Boswell R"]}, {"title": "Redefinition of the self-bias voltage in a dielectrically shielded thin sheath RF discharge", "year": "2018", "source": "Journal of Applied Physics, vol. 123, no. 19, pp. 1-15", "authors": ["Ho T", "Christine Charles", "Boswell R"]}, {"title": "Selective radial release of hot, magnetised electrons downstream of a low-pressure expanding plasma", "year": "2018", "source": "Journal of Physics D: Applied Physics, vol. 51, no. 37, pp. 1-7", "authors": ["Bennet A", "Christine Charles", "Boswell R"]}, {"title": "Spatio-temporal plasma heating mechanisms in a radio frequency electrothermal microthruster", "year": "2018", "source": "Plasma Sources Science and Technology, vol. 27, no. 8, pp. 17pp", "authors": ["Doyle S", "Gibson A", "Flatt J", "Christine Charles"]}, {"title": "Separating the location of geometric and magnetic expansions in low-pressure expanding plasmas", "year": "2018", "source": "Plasma Sources Science and Technology, vol. 27, no. 7, pp. 1pp", "authors": ["Bennet A", "Christine Charles", "Boswell R"]}, {"title": "n integrated RF power delivery and plasma micro-thruster system for nano-satellites", "year": "2018", "source": "Frontiers in Physics, vol. 6, no. 115, pp. 1-9pp", "authors": ["Liang W", "Christine Charles", "Raymond L"]}, {"title": "Demonstrating a new technology for space debris removal using a bi-directional plasma thruster", "year": "2018", "source": "Scientific Reports, vol. 8, pp. 1-10", "authors": ["Takahashi K", "Christine Charles", "Boswell R"]}, {"title": "Laboratory demonstration of space debris removal by a bi-directional helicon plasma thruster", "year": "2017", "source": "68th International Astronautical Congress: Unlocking Imagination, Fostering Innovation and Strengthening Security, IAC 2017, International Astronautical Federation (IAF), TBC, pp. 3709-3715pp", "authors": ["Takahashi K", "Christine Charles", "Boswell R"]}, {"title": "Revisiting the thermodynamics of collisionless plasma expansion in solar magnetic funnels", "year": "2017", "source": "68th International Astronautical Congress: Unlocking Imagination, Fostering Innovation and Strengthening Security, IAC 2017, International Astronautical Federation (IAF), TBC, pp. 4306-4309pp", "authors": ["Zhang Y", "Christine Charles", "Boswell R"]}, {"title": "The mini-helicon thruster for", "year": "2017", "source": "CubeSat' nano-satellites: Experiments and simulations'68th International Astronautical Congress: Unlocking Imagination, Fostering Innovation and Strengthening Security, IAC 2017, International Astronautical Federation (IAF), TBC, pp. 8813-8816pp", "authors": ["Bennet A", "Takahashi K", "Christine Charles"]}, {"title": "The pocket rocket electro-thermal plasma thruster for", "year": "2017", "source": "CubeSat' nano-satellites'68th International Astronautical Congress: Unlocking Imagination, Fostering Innovation and Strengthening Security, IAC 2017, International Astronautical Federation (IAF), TBC, pp. 9035-9039", "authors": ["Christine Charles", "Boswell R", "Ho T"]}, {"title": "Cross-field transport of electrons at the magnetic throat in an annular plasma reactor", "year": "2017", "source": "Journal of Physics D: Applied Physics, vol. 50, no. 1, pp. 7pp", "authors": ["Zhang Y", "Christine Charles", "Boswell R"]}, {"title": "High temperature electrons exhausted from rf plasma sources along a magnetic nozzle", "year": "2017", "source": "AIP Conference Proceedings, vol. 24, pp. 5pp", "authors": ["Takahashi K", "Akahoshi H", "Christine Charles"]}, {"title": "Vacuum Testing of a miniaturized Switch Mode Amplifier Powering an Electrothermal Plasma Micro-Thruster", "year": "2017", "source": "Frontiers in Physics, vol. 5, no. 36, p. 8", "authors": ["Christine Charles", "Liang W", "Raymond L"]}, {"title": "compact RF power inverter with reduced EMI for a CubeSat electrothermal micro-Thruster", "year": "2017", "source": "18th IEEE Workshop on Control and Modeling for Power Electronics, COMPEL 2017, Conference Organising Committee, TBC, pp. 6pp", "authors": ["Liang W", "Cui X", "Raymond L", "Christine Charles"]}, {"title": "Comprehensive Cold Gas Performance Study of the Pocket Rocket Radiofrequency Electrothermal Microthruster", "year": "2017", "source": "Frontiers in Physics, vol. 4, no. 55, pp. 16pp", "authors": ["Ho T", "Christine Charles", "Boswell R"]}, {"title": "Structurally supportive RF power inverter for a CubeSat electrothermal plasma micro-thruster with PCB inductors", "year": "2017", "source": "32nd Annual IEEE Applied Power Electronics Conference and Exposition, APEC 2017, Institute of Electrical and Electronics Engineers (IEEE Inc), USA, pp. 2141-2145", "authors": ["Liang W", "Raymond L", "Davila J", "Christine Charles"]}, {"title": "Neutral gas heating and ion transport in a constricted plasma flow", "year": "2017", "source": "Physics of Plasmas, vol. 24, no. 8, pp. 084501 (1-5 pp)", "authors": ["Ho T", "Christine Charles", "Boswell R"]}, {"title": "Microplasma Array Patterning of Reactive Oxygen and Nitrogen Species onto Polystyrene", "year": "2017", "source": "Physics of Plasmas, vol. 5, pp. 1-12pp", "authors": ["Szili E", "Dedrick J", "Oh J", "Christine Charles"]}, {"title": "Density Measurements in Low Pressure, Weakly Magnetized, RF Plasmas: Experimental Veri\u00ef\u00ac?cation of the Sheath Expansion Effect", "year": "2017", "source": "Frontiers in Physics, vol. 5, pp. 6pp.", "authors": ["Zhang Y", "Christine Charles", "Boswell R"]}, {"title": "Short Review of Experimental and Computational Diagnostics for Radiofrequency Plasma Micro-thrusters", "year": "2016", "source": "Plasma Chemistry and Plasma Processing, vol. 36, no. 1, pp. 29-44pp", "authors": ["Christine Charles", "Bish A", "Boswell R"]}, {"title": "Neutral gas temperature estimates and metastable resonance energy transfer for argon-nitrogen discharges", "year": "2016", "source": "Physics of Plasmas, vol. 23, no. 1, pp. -", "authors": ["Greig A", "Christine Charles", "Boswell R"]}, {"title": "Collisionless expansion of pulsed radio frequency plasmas. II. Parameter study", "year": "2016", "source": "Physics of Plasmas, vol. 23, no. 1, pp. 1-8", "authors": ["Schroder T", "Grulke O", "Klinger T", "Christine Charles"]}, {"title": "Collisionless expansion of pulsed radio frequency plasmas. I. Front formation", "year": "2016", "source": "Physics of Plasmas, vol. 23, no. 1, pp. 1-11", "authors": ["Schroder T", "Grulke O", "Klinger T", "Christine Charles"]}, {"title": "Characterization of an annular helicon plasma source powered by an outer or inner RF antenna", "year": "2016", "source": "Plasma Sources Science and Technology, vol. 25, no. 1, pp. 015007 (9 pp)", "authors": ["Zhang Y", "Christine Charles", "Boswell R"]}, {"title": "Measurement of bi-directional ion acceleration along a convergent-divergent magnetic nozzle", "year": "2016", "source": "Applied Physics Letters, vol. 108, no. 10, p. 104101", "authors": ["Zhang Y", "Christine Charles", "Boswell R"]}, {"title": "Thermodynamic Study on Plasma Expansion along a Divergent Magnetic Field", "year": "2016", "source": "Physical Review Letters, vol. 116, no. 2, pp. 1-5", "authors": ["Zhang Y", "Christine Charles", "Boswell R"]}, {"title": "Plasma Catalytic Synthesis of Ammonia Using Functionalized-Carbon Coatings in an Atmospheric-Pressure Non-equilibrium Discharge", "year": "2016", "source": "Plasma Chemistry and Plasma Processing, vol. 36, no. 4, pp. 917-940", "authors": ["Hong J", "Aramesh M", "Shimoni O", "Christine Charles"]}, {"title": "Effect of radial plasma transport at the magnetic throat on axial ion beam formation", "year": "2016", "source": "Physics of Plasmas, vol. 23, no. 8, p. 083515", "authors": ["Zhang Y", "Christine Charles", "Boswell R"]}, {"title": "Direct Measurement of Axial Momentum Imparted by an Electrothermal Radiofrequency Plasma Micro-Thruster", "year": "2016", "source": "Frontiers in Physics, vol. 4, pp. (6pp)", "authors": ["Christine Charles", "Boswell R", "Bish A"]}, {"title": "POLYTROPIC MODEL for SPACE and LABORATORY PLASMAS DESCRIBED by BI-MAXWELLIAN ELECTRON DISTRIBUTIONS", "year": "2016", "source": "The Astrophysical Journal, vol. 829, no. 1, pp. -", "authors": ["Zhang Y", "Christine Charles", "Boswell R"]}, {"title": "How plasma induced oxidation, oxygenation, and de-oxygenation influences viability of skin cells", "year": "2016", "source": "Applied Physics Letters, vol. 109, no. 20, p. 203701", "authors": ["Oh J", "Strudwick X", "Short R", "Christine Charles"]}, {"title": "pproximants to the Tonks-Langmuir theory for a collisionless annular plasma", "year": "2015", "source": "Physical Review E-Statistical, Nonlinear and Soft Matter Physics, vol. 92, no. 6, pp. 63103-63103", "authors": ["Zhang Y", "Christine Charles", "Boswell R"]}, {"title": "Simulation of main plasma parameters of a cylindrical asymmetric capacitively coupled plasma micro-thruster using computational fluid dynamics", "year": "2015", "source": "Frontiers in Physics, vol. 2, no. 80, pp. 1-9", "authors": ["Greig A", "Christine Charles", "Boswell R"]}, {"title": "Nanotechnology, Plasma, Hydrogen from Artificial Photosynthesis, and Fuel cells: Powering the Developing World to the Sustainocene", "year": "2015", "source": "in Thomas Alured Faunce (ed.), Nanotechnology Toward the Sustainocene, Pan Stanford Publishing, Singapore, pp. 241-257", "authors": ["Faunce T", "Christine Charles"]}, {"title": "Principle of radial transport in low temperature annular plasmas", "year": "2015", "source": "Physics of Plasmas, vol. 22, no. 7", "authors": ["Zhang Y", "Christine Charles", "Boswell R"]}, {"title": "Spatiotemporal study of gas heating mechanisms in a radio-frequency electrothermal plasma micro-thruster", "year": "2015", "source": "Frontiers in Physics, vol. 3, pp. 84 (1-7pp)", "authors": ["Greig A", "Christine Charles", "Boswell R"]}, {"title": "Particle in cell simulation of a radiofrequency plasma jet expanding in vacuum", "year": "2015", "source": "Applied Physics Letters, vol. 106, no. 9, pp. 093502/1-4", "authors": ["Christine Charles", "Hawkins R", "Boswell R"]}, {"title": "Non-local electron energy probability function in a plasma expanding along a magnetic nozzle", "year": "2015", "source": "Frontiers in Physics, vol. 3, no. 14, pp. 1-5", "authors": ["Boswell R", "Takahashi K", "Christine Charles"]}, {"title": "Grand Challenges in low-temperature plasma physics", "year": "2014", "source": "Frontiers in Physics, vol. 2, no. 39, pp. 1-5", "authors": ["Christine Charles"]}, {"title": "Phase resolved imaging of a repetitive extrusion of hydrogen plasma from a hollow cathode source", "year": "2014", "source": "IEEE Transactions on Plasma Science, vol. 42, no. 10, pp. 2834-2835", "authors": ["Dixon S", "Dedrick J", "Christine Charles"]}, {"title": "Effect of magnetic and physical nozzles on plasma thruster performance", "year": "2014", "source": "Plasma Sources Science and Technology, vol. 23, no. 4, pp. 044004/1-9", "authors": ["Takahashi K", "Christine Charles", "Boswell R"]}, {"title": "Transport of ion beam in an annular magnetically expanding helicon double layer thruster", "year": "2014", "source": "Physics of Plasmas, vol. 21, no. 6, pp. 063511/1-5", "authors": ["Zhang Y", "Christine Charles", "Boswell R"]}, {"title": "Volume and surface propellant heating in an electrothermal radio-frequency plasma micro-thruster", "year": "2014", "source": "Applied Physics Letters, vol. 105, no. 5, pp. 054102/1-4", "authors": ["Greig A", "Christine Charles", "Paulin N"]}, {"title": "Observations of a mode transition in a hydrogen hollow cathode discharge using phase resolved optical emission spectroscopy", "year": "2014", "source": "Applied Physics Letters, vol. 105, no. 1, p. 014104", "authors": ["Dixon S", "Christine Charles", "Dedrick J"]}, {"title": "n experimental and analytical study of an asymmetric capacitively coupled plasma used for plasma polymerization", "year": "2014", "source": "Plasma Processes and Polymers, vol. 11, no. 9, pp. 833-841", "authors": ["Michelmore A", "Whittle J", "Short R", "Christine Charles"]}, {"title": "Plume characteristics of an electrothermal plasma microthruster", "year": "2014", "source": "IEEE Transactions on Plasma Science, vol. 42, no. 10, pp. 2728-2729", "authors": ["Greig A", "Christine Charles", "Boswell R"]}, {"title": "Collisionless expansion of pulsed rf plasmas", "year": "2014", "source": "Journal of Physics D: Applied Physics, vol. 47, no. 5, pp. 1-7", "authors": ["Schr\u00c3\u00b6der T", "Grulke O", "Klinger T", "Christine Charles"]}, {"title": "Low-Weight Fixed Ceramic Capacitor Impedance Matching System for an Electrothermal Plasma Microthruster", "year": "2014", "source": "Journal of Propulsion and Power, vol. 30, no. 4, pp. 1117-1121", "authors": ["Christine Charles", "Boswell R", "Bish A"]}, {"title": "Formation of spatially periodic fronts of high-energy electrons in a radio-frequency driven surface microdischarge", "year": "2013", "source": "Applied Physics Letters, vol. 102, no. 3, p. 5", "authors": ["Dedrick J", "O'Connell D", "Gans T", "Christine Charles"]}, {"title": "pproaching the Theoretical Limit of Diamagnetic-Induced Momentum in a Rapidly Diverging Magnetic Nozzle", "year": "2013", "source": "Physical Review Letters, vol. 110, no. 19, p. 5", "authors": ["Takahashi K", "Christine Charles", "Boswell R"]}, {"title": "Interactions between arrayed hollow cathodes", "year": "2013", "source": "Journal of Physics D: Applied Physics, vol. 46, no. 14, p. 9", "authors": ["Dixon S", "Christine Charles", "Boswell R"]}, {"title": "Boltzmann expansion in a radiofrequency conical helicon thruster operating in xenon and argon", "year": "2013", "source": "Applied Physics Letters, vol. 102, no. 22, pp. 223510/ 1-4", "authors": ["Christine Charles", "Boswell R", "Takahashi K"]}, {"title": "Variable frequency matching to a radiofrequency source immersed in vacuum", "year": "2013", "source": "Journal of Physics D: Applied Physics, vol. 46, no. 36, p. 365203", "authors": ["Christine Charles", "Boswell R", "Bishop A"]}, {"title": "Spatial evolution of EEPFs in a millimetre scale radio frequency argon plume", "year": "2013", "source": "Journal of Physics D: Applied Physics, vol. 46, no. 36, p. 365202", "authors": ["Dixon S", "Christine Charles", "Boswell R"]}, {"title": "Direct measurement of neutral gas heating in a radio-frequency electrothermal plasma micro-thruster", "year": "2013", "source": "Applied Physics Letters, vol. 103, no. 7, p. 074101", "authors": ["Greig A", "Christine Charles", "Hawkins R"]}, {"title": "Performance improvement of a permanent magnet helicon plasma thruster", "year": "2013", "source": "Journal of Physics D: Applied Physics, vol. 46, no. 35, p. 352001", "authors": ["Takahashi K", "Christine Charles", "Boswell R"]}, {"title": "Nanosecond optical imaging spectroscopy of an electrothermal radiofrequency plasma thruster plume", "year": "2013", "source": "Applied Physics Letters, vol. 103, no. 12, p. 124103", "authors": ["Christine Charles", "Dedrick J", "Boswell R"]}, {"title": "Surface discharge plasma actuator driven by a pulsed 13.56 MHz-5 kHz voltage waveform", "year": "2013", "source": "Journal of Physics D: Applied Physics, vol. 46, no. 40, p. 405201", "authors": ["Dedrick J", "Im S", "Cappelli M", "Christine Charles"]}, {"title": "Defining plasma polymerization: New insight into what we should be measuring", "year": "2013", "source": "ACS Applied Materials and Interfaces, vol. 5, no. 12, pp. 5387-5391", "authors": ["Michelmore A", "Christine Charles", "Boswell R"]}, {"title": "Induced Flow and Optical Emission Generated by a Pulsed 13.56 MHz-5 kHz Plasma Actuator", "year": "2013", "source": "IEEE Transactions on Plasma Science, vol. 41, no. 12, pp. 3275-3278", "authors": ["Dedrick J", "Im S", "Cappelli M", "Christine Charles"]}, {"title": "radio frequency plasma micro-thruster: Characterization of various discharge gases through optical diagnostics", "year": "2013", "source": "American Institute of Aeronautics and Astronautics (AIAA)San Jose, CA", "authors": ["Greig A", "Christine Charles", "Boswell R", "eds"]}, {"title": "Simulations of electron heating in a capacitively coupled radio frequency micro-thruster using computational fluid dynamics", "year": "2013", "source": "Conference Organising CommitteeSan Diego, CA", "authors": ["Greig A", "Christine Charles", "Boswell R", "eds"]}, {"title": "One step multifunctional micropatterning of surfaces using asymmetric glow discharge plasma polymerization", "year": "2012", "source": "Chemical Communications, vol. 48, no. 13, pp. 1907-1909", "authors": ["Menzies D", "Gengenbach T", "Forsythe J", "Christine Charles"]}, {"title": "magnetic nozzle calculation of the force on a plasma", "year": "2012", "source": "Physics of Plasmas, vol. 19, no. 3, p. 033507", "authors": ["Fruchtman A", "Takahashi K", "Christine Charles"]}, {"title": "xial force imparted by a conical radiofrequency magneto-plasma thruster", "year": "2012", "source": "Applied Physics Letters, vol. 100, no. 11, p. 113504", "authors": ["Christine Charles", "Takahashi K", "Boswell R"]}, {"title": "Measurement and modelling of a radiofrequency micro-thruster", "year": "2012", "source": "Plasma Sources Science and Technology, vol. 21, no. 2, p. 022002", "authors": ["Christine Charles", "Boswell R"]}, {"title": "Current-Free Double Layer in Magnetically Expanding RF Plasmas", "year": "2012", "source": "Journal of Plasma and Fusion Research, vol. 88, no. 4, pp. 220-227", "authors": ["Takahashi K", "Christine Charles", "Boswell R"]}, {"title": "xial force imparted by a current-free magnetically expanding plasma", "year": "2012", "source": "Physics of Plasmas, vol. 19, no. 8, p. 083509", "authors": ["Takahashi K", "Lafleur T", "Christine Charles"]}, {"title": "Control of diffuse and filamentary modes in an RF asymmetric surface barrier discharge in atmospheric-pressure argon", "year": "2012", "source": "Plasma Sources Science and Technology, vol. 21, no. 5, pp. 055016 (7)", "authors": ["Dedrick J", "Boswell R", "Rabat H", "Christine Charles"]}, {"title": "Platinum nanocluster growth on vertically aligned carbon nanofiber arrays: Sputtering experiments and molecular dynamics simulations", "year": "2012", "source": "Applied Surface Science, vol. 263, pp. 352-356", "authors": ["Brault P", "Caillard A", "Christine Charles"]}, {"title": "Investigation of radiofrequency plasma sources for space travel", "year": "2012", "source": "Plasma Physics and Controlled Fusion, vol. 54, no. 12, pp. 1-7", "authors": ["Christine Charles", "Boswell R", "Takahashi K"]}, {"title": "Propagation Structure of a 13.56-MHz Asymmetric Surface Barrier Discharge Plasma in Atmospheric-Pressure Air", "year": "2011", "source": "IEEE Transactions on Plasma Science, vol. 39, no. 11, pp. 2082-2083", "authors": ["Dedrick J", "Boswell R", "Audier P", "Christine Charles"]}, {"title": "Investigation of effect of excitation frequency on electron energy distribution functions in low pressure radio frequency bounded plasmas", "year": "2011", "source": "Physics of Plasmas, vol. 18, no. 7, pp. 072102-7", "authors": ["Bhattacharjee S", "Lafleur T", "Christine Charles"]}, {"title": "Electron temperature characterization and power balance in a low magnetic field helicon mode", "year": "2011", "source": "Journal of Physics D: Applied Physics, vol. 44, no. 18, pp. 185204-12", "authors": ["Lafleur T", "Christine Charles", "Boswell R"]}, {"title": "Direct thrust measurements and modelling of a radio-frequency expanding plasma thruster", "year": "2011", "source": "Physics of Plasmas, vol. 18, no. 8, p. 4", "authors": ["Lafleur T", "Takahashi K", "Christine Charles"]}, {"title": "Microarcing in a Helicon Plasma Reactor", "year": "2011", "source": "IEEE Transactions on Plasma Science, vol. 39, no. 8, pp. 1652-1659", "authors": ["Ling J", "Boswell R", "Lafleur T", "Christine Charles"]}, {"title": "Characterization of nanocrystalline nitrogen-containing titanium oxide obtained by N2/O2/Ar low-field helicon plasma sputtering", "year": "2011", "source": "Journal of Physics D: Applied Physics, vol. 44, no. 45, p. 8", "authors": ["Sarra-Bournet C", "Haberl B", "Christine Charles"]}, {"title": "Plasma Expansion From a Radio Frequency Microdischarge", "year": "2011", "source": "IEEE Transactions on Plasma Science, vol. 39, no. 11, pp. 2512-2513", "authors": ["Boswell R", "Christine Charles", "Alexander P"]}, {"title": "Ion-Current Downstream of a Carbon Dioxide Helicon Double Layer", "year": "2011", "source": "IEEE Transactions on Plasma Science, vol. 39, no. 11, pp. 2446-2447", "authors": ["Christine Charles", "Hawkins R", "Boswell R"]}, {"title": "Mode Transitions in the Helicon Double-Layer Thruster Prototype Operating in Xenon", "year": "2011", "source": "IEEE Transactions on Plasma Science, vol. 39, no. 11, pp. 2468-2469", "authors": ["West M", "Christine Charles", "Boswell R"]}, {"title": "Electron Diamagnetic Effect on Axial Force in an Expanding Plasma: Experiments and Theory", "year": "2011", "source": "Physical Review Letters, vol. 107, no. 23, pp. 235001-4", "authors": ["Takahashi K", "Lafleur T", "Christine Charles"]}, {"title": "Three-Dimensional Magnetic Field Mapping of the Magnetically Steered Helicon Double-Layer Thruster", "year": "2011", "source": "IEEE Transactions on Plasma Science, vol. 39, no. 11, pp. 2460-2461", "authors": ["Cox W", "Hawkins R", "Christine Charles"]}, {"title": "Electron-cyclotron damping of helicon waves in low diverging magnetic fields", "year": "2011", "source": "Physics of Plasmas, vol. 18, no. 4, pp. 043502-12", "authors": ["Lafleur T", "Christine Charles", "Boswell R"]}, {"title": "Plasma propulsion", "year": "2008", "source": "Australian Physics, vol. 45, no. 6, pp. 196-198", "authors": ["Christine Charles"]}, {"title": "Electron Energy Distribution of a Current-Free Double Layer: Druyvesteyn Theory and Experiments", "year": "2011", "source": "Physical Review Letters, vol. 107, no. 3, p. 4", "authors": ["Takahashi K", "Christine Charles", "Boswell R"]}, {"title": "Children of the stars, plasma is the fourth state of matter", "year": "2011", "source": "in Chris Stewart (ed.), Light & Matter, University of Sydney, Australia, pp. 27-41pp.", "authors": ["Christine Charles"]}, {"title": "Direct thrust measurement of a permanent magnet helicon double layer thruster", "year": "2011", "source": "Applied Physics Letters, vol. 98, pp. 141503 -1/3", "authors": ["Takahashi K", "Lafleur T", "Christine Charles"]}, {"title": "Particle-in-cell simulations of a current-free double layer", "year": "2011", "source": "Physics of Plasmas, vol. 18, no. 6, p. 11", "authors": ["Baalrud S", "Lafleur T", "Boswell R", "Christine Charles"]}, {"title": "Characterization of a helicon plasma source in low diverging magnetic fields", "year": "2011", "source": "Journal of Physics D: Applied Physics, vol. 44, no. 5, pp. 055202 (11)", "authors": ["Lafleur T", "Christine Charles", "Boswell R"]}, {"title": "Characterization of the ion beam formed in a low magnetic field helicon mode", "year": "2011", "source": "Journal of Physics D: Applied Physics, vol. 44, no. 14, p. 13", "authors": ["Lafleur T", "Christine Charles", "Boswell R"]}, {"title": "Plasma propagation of a 13.56 MHz asymmetric surface barrier discharge in atmospheric pressure air", "year": "2011", "source": "Journal of Physics D: Applied Physics, vol. 44, no. 20, p. 8", "authors": ["Dedrick J", "Boswell R", "Audier P", "Christine Charles"]}, {"title": "Performance characterization of a helicon double layer thruster using direct thrust measurements", "year": "2011", "source": "Journal of Physics D: Applied Physics, vol. 44, no. 23, p. 5", "authors": ["Pottinger S", "Lappas V", "Christine Charles"]}, {"title": "Low temperature growth of nanocrystalline TiO2 films with Ar/O2 low-field helicon plasma", "year": "2011", "source": "Surface and Coatings Technology, vol. 205, no. 15, pp. 3939-3946", "authors": ["Sarra-Bournet C", "Christine Charles", "Boswell R"]}, {"title": "Magnetic Ion Beam Deflection in the Helicon Double-Layer Thruster", "year": "2010", "source": "Journal of Propulsion and Power, vol. 26, no. 5, pp. 1045-1052", "authors": ["Cox W", "Christine Charles", "Boswell R"]}, {"title": "Experimental investigation of a conical helicon double layer thruster arrangement", "year": "2010", "source": "Plasma Sources Science and Technology, vol. 19, no. 4, pp. 045003 (9)", "authors": ["Christine Charles", "Cox W", "Boswell R"]}, {"title": "Thrust measurements in a low-magnetic field high-density mode in the helicon double layer thruster", "year": "2010", "source": "Journal of Physics D: Applied Physics, vol. 43, no. 30, pp. 305203 (9)", "authors": ["Ling J", "West M", "Lafleur T", "Christine Charles"]}, {"title": "Characterization of the temperature of free electrons diffusing from a magnetically expanding current-free double layer plasma", "year": "2010", "source": "Journal of Physics D: Applied Physics, vol. 43, no. 16, pp. 162001 (4)", "authors": ["Takahashi K", "Christine Charles", "Boswell R"]}, {"title": "symmetric surface barrier discharge plasma driven by pulsed 13.56MHz power in atmospheric pressure air", "year": "2010", "source": "Journal of Physics D: Applied Physics, vol. 43, no. 34, pp. 342001 (6)", "authors": ["Dedrick J", "Boswell R", "Christine Charles"]}, {"title": "Ion beam formation in a very low magnetic field expanding helicon discharge", "year": "2010", "source": "Physics of Plasmas, vol. 17, no. 4, p. 043505", "authors": ["Lafleur T", "Christine Charles", "Boswell R"]}, {"title": "Operating Radio Frequency Antennas Immersed in Vacuum: Implications for Ground-Testing Plasma Thrusters", "year": "2010", "source": "Journal of Propulsion and Power, vol. 26, no. 4, pp. 892-896", "authors": ["West M", "Christine Charles", "Boswell R"]}, {"title": "High density conics in a magnetically expanding helicon plasma", "year": "2010", "source": "Applied Physics Letters, vol. 96, no. 5, p. 3", "authors": ["Christine Charles"]}, {"title": "Plasma control by modification of helicon wave propagation in low magnetic fields", "year": "2010", "source": "Physics of Plasmas, vol. 17, no. 7, pp. 073508/1-12", "authors": ["Lafleur T", "Christine Charles", "Boswell R"]}, {"title": "Double-layer ion acceleration triggered by ion magnetization in expanding radiofrequency plasma sources", "year": "2010", "source": "Applied Physics Letters, vol. 97, p. 141503", "authors": ["Takahashi K", "Christine Charles", "Boswell R"]}, {"title": "Carbon/platinum nanotextured films produced by plasma sputtering", "year": "2009", "source": "Carbon, vol. 47, pp. 209-214", "authors": ["Rabat H", "Andreazza C", "Brault P", "Christine Charles"]}, {"title": "Detailed plasma potential measurements in a radio-frequency expanding plasma obtained from various electrostatic probes", "year": "2009", "source": "Physics of Plasmas, vol. 16, no. 044510, p. 4", "authors": ["Lafleur T", "Christine Charles", "Boswell R"]}, {"title": "nomalous Diffusion Mediated by Atom Deposition into a Porous Substrate", "year": "2009", "source": "Physical Review Letters, vol. 012, no. 4 (2009), pp. 045901 - 4", "authors": ["Brault P", "Josserand C", "Bauchire J", "Christine Charles"]}, {"title": "Oblique Double Layers: A Comparison between Terrestrial and Auroral Measurements", "year": "2009", "source": "Physical Review Letters, vol. 103, no. 095001, p. 4", "authors": ["Christine Charles", "Boswell R", "Hawkins R"]}, {"title": "Effect of Nafion and platinum content in a catalyst layer processed in a radio frequency helicon plasma system", "year": "2009", "source": "Journal of Physics D: Applied Physics, vol. 42, no. 045207, p. 9", "authors": ["Caillard A", "Christine Charles", "Ramdutt D"]}, {"title": "high sensitivity momentum flux measuring instrument for plasma thruster exhausts and diffusive plasmas", "year": "2009", "source": "Review of Scientific Instruments, vol. 80, no. 053509, p. 9", "authors": ["West M", "Christine Charles", "Boswell R"]}, {"title": "Plasmas for spacecraft propulsion", "year": "2009", "source": "Journal of Physics D: Applied Physics, vol. 42, no. 163001, p. 18", "authors": ["Christine Charles"]}, {"title": "High density mode in xenon produced by a Helicon Double Layer Thruster", "year": "2009", "source": "Journal of Physics D: Applied Physics, vol. 42, no. 24, pp. 245201 (9)", "authors": ["West M", "Christine Charles", "Boswell R"]}, {"title": "Erratum: \"Double layer in an expanding plasma: Simultaneous upstream and downstream measurements\"", "year": "2009", "source": "Physics of Plasmas, vol. 16, no. 7, p. 079903", "authors": ["Byhring H", "Christine Charles", "Fredriksen A"]}, {"title": "Transport of energetic electrons in a magnetically expanding helicon double layer plasma", "year": "2009", "source": "Applied Physics Letters, vol. 94, no. 191503, p. 3", "authors": ["Takahashi K", "Christine Charles", "Boswell R"]}, {"title": "TCP Plasma Sputtering of Nanostructured Fuel Cell Electrodes", "year": "2008", "source": "IEEE Transactions on Plasma Science, vol. 36, no. 4, pp. 872-873", "authors": ["Rabat H", "Andreazza C", "Brault P", "Christine Charles"]}, {"title": "Operating the Helicon Double Layer Thruster in a Space Simulation Chamber", "year": "2008", "source": "IEEE Transactions on Plasma Science, vol. 36, no. 4, pp. 1196-1197", "authors": ["Christine Charles", "Boswell R", "Alexander P"]}, {"title": "Synthesis of Carbon Nanofibers and Pt-Nanocluster-Based Electrochemical Microsystems by Combining Low-Pressure Helicon Plasma Techniques", "year": "2008", "source": "IEEE Transactions on Plasma Science, vol. 36, no. 4, pp. 882-883", "authors": ["Caillard A", "Christine Charles", "Boswell R"]}, {"title": "Transport and Deposition of Plasma-Sputtered Platinum Atoms: Comparison Between Experiments and Simulation", "year": "2008", "source": "IEEE Transactions on Plasma Science, vol. 36, no. 4, pp. 884-885", "authors": ["Caillard A", "Christine Charles", "Boswell R"]}, {"title": "Deposition of platinum catalyst by plasma sputtering for fuel cells: 3D simulation and experiments", "year": "2008", "source": "Plasma Sources Science and Technology, vol. 17, pp. 035028 1-17", "authors": ["Caillard A", "Christine Charles", "Boswell R"]}, {"title": "Radial characterization of the electron energy distribution in a helicon source terminated by a double layer", "year": "2008", "source": "Physics of Plasmas, vol. 15, no. 074505, pp. 1-4", "authors": ["Takahashi K", "Christine Charles", "Boswell R"]}, {"title": "Double layer in an expanding plasma: Simultaneous upstream and downstream measurements", "year": "2008", "source": "Physics of Plasmas, vol. 15, pp. 102113-1 - 102113-6", "authors": ["Byhring H", "Christine Charles", "Fredriksen A"]}, {"title": "Improvement of the sputtered platinum utilization in proton exchange membrane fuel cells using plasma-based carbon nanofibres", "year": "2008", "source": "Journal of Physics D: Applied Physics, vol. 41, pp. 1-10", "authors": ["Caillard A", "Christine Charles", "Boswell R"]}, {"title": "n experimental investigation of alternative propellants for the helicon double layer thruster", "year": "2008", "source": "Journal of Physics D: Applied Physics, vol. 41, pp. 175213 - 1-6", "authors": ["Christine Charles", "Boswell R", "Laine R"]}, {"title": "Xenon Ion Beam Detachment From a Helicon Double Layer Thruster", "year": "2008", "source": "IEEE Transactions on Plasma Science, vol. 36, no. 4, pp. 1194-1195", "authors": ["Gesto F", "Christine Charles", "Boswell R"]}, {"title": "Effect of Exhaust Magnetic Field in a Helicon Double-Layer Thruster Operating in Xenon", "year": "2008", "source": "IEEE Transactions on Plasma Science, vol. 36, no. 5, pp. 2141-2146", "authors": ["Christine Charles", "Boswell R"]}, {"title": "Three-Dimensional Mapping of Ion Density in a Double-Layer Helicon Plasma", "year": "2008", "source": "IEEE Transactions on Plasma Science, vol. 36, no. 4, pp. 1386-1387", "authors": ["Cox W", "Hawkins R", "Christine Charles"]}, {"title": "Spatial retarding field energy analyzer measurements downstream of a helicon double layer plasma", "year": "2008", "source": "Applied Physics Letters, vol. 93, no. 071505, pp. 1-3", "authors": ["Cox W", "Christine Charles", "Boswell R"]}, {"title": "Testing a Helicon Double Layer Thruster Immersed in a Space-Simulation Chamber", "year": "2008", "source": "Journal of Propulsion and Power, vol. 24, no. 1, pp. 134-141", "authors": ["West M", "Christine Charles", "Boswell R"]}, {"title": "Spatial evolution of an ion beam created by a geometrically expanding low-pressure argon plasma", "year": "2008", "source": "Applied Physics Letters, vol. 92, pp. 221508-1 - 221508-3", "authors": ["Corr C", "Boswell R", "Christine Charles"]}, {"title": "Magnetic steering of a helicon double layer thruster", "year": "2008", "source": "Applied Physics Letters, vol. 93, pp. 201501-1 - 201501-3", "authors": ["Christine Charles", "Boswell R", "Cox W"]}, {"title": "The magnetic-field-induced transition from an expanding plasma to a double layer containing expanding plasma", "year": "2007", "source": "Applied Physics Letters, vol. 91, no. 20, pp. 1-3", "authors": ["Christine Charles", "Boswell R"]}, {"title": "Low energy plasma treatment of a proton exchange membrane used for low temperature fuel cells", "year": "2007", "source": "Plasma Physics and Controlled Fusion, vol. 49, no. 2007, pp. A73-A79", "authors": ["Christine Charles", "Ramdutt D", "Brault P"]}, {"title": "Integrated plasma synthesis of efficient catalytic nanostructures for fuel cell electrodes", "year": "2007", "source": "Nanotechnology, vol. 18, pp. 305603 1-9", "authors": ["Caillard A", "Christine Charles", "Boswell R"]}, {"title": "Measurement of the energy distribution of trapped and free electrons in a current-free double layer", "year": "2007", "source": "Physics of Plasmas, vol. 14, pp. 114503 1-4", "authors": ["Takahashi T", "Christine Charles", "Boswell R"]}, {"title": "Low energy plasma treatment of Nafion membranes for PEM fuel cells", "year": "2007", "source": "Journal of Power Sources, vol. 165, pp. 41-48", "authors": ["Ramdutt D", "Christine Charles", "Hudspeth J"]}, {"title": "Ion beam formation in a low-pressure geometrically expanding argon plasma", "year": "2007", "source": "Applied Physics Letters, vol. 91, pp. 241501 1-3", "authors": ["Corr C", "Zanger J", "Boswell R", "Christine Charles"]}, {"title": "review of recent laboratory double layer experiments", "year": "2007", "source": "Plasma Sources Science and Technology, vol. 16, pp. R1-R25", "authors": ["Christine Charles"]}, {"title": "Plasma based platinum nanoaggregates deposited on carbon nanofibers improve fuel cell efficiency", "year": "2007", "source": "Applied Physics Letters, vol. 90, no. 22, pp. 223119 1-3", "authors": ["Caillard A", "Christine Charles", "Boswell R"]}, {"title": "The current-free electric double layer in a coronal magnetic funnel", "year": "2006", "source": "The Astrophysical Journal, vol. 640, pp. L199-L202", "authors": ["Boswell R", "Marsch E", "Christine Charles"]}, {"title": "Upstream Ionization Instability Associated with a Current-Free Double Layer", "year": "2006", "source": "Physical Review Letters, vol. 97, no. 7, pp. 075003-1-4", "authors": ["Aanesland A", "Christine Charles", "Lieberman M"]}, {"title": "Plasma expansion from a dielectric electron cyclotron resonance source", "year": "2006", "source": "Physica Scripta, vol. T122, pp. 19-24", "authors": ["Aanesland A", "Christine Charles"]}, {"title": "Xenon ion beam characterization in a helicon double layer thruster", "year": "2006", "source": "Applied Physics Letters, vol. 89, no. 26, pp. 261503-1-3", "authors": ["Christine Charles", "Boswell R", "Lieberman M"]}, {"title": "Solid polymer fuel cell synthesis by low pressure plasmas: a short review", "year": "2006", "source": "European Physical Journal - Applied Physics, vol. 34, pp. 151-156", "authors": ["Brault P", "Roualdes S", "Caillard A", "Christine Charles"]}, {"title": "Interface creation and stress dynamics in plasma-deposited silicon dioxide films", "year": "2006", "source": "Applied Physics Letters, vol. 88, no. 23, pp. 234103-1-3", "authors": ["Au V", "Christine Charles", "Boswell R"]}, {"title": "Theory for Formation of a Low-Pressure, Current-Free Double Layer", "year": "2006", "source": "Physical Review Letters, vol. 97, no. 4, pp. 045003-1-4", "authors": ["Lieberman M", "Christine Charles"]}, {"title": "Experiments and theory of an upstream ionization instability excited by an accelerated electron beam through a current-free double layer", "year": "2006", "source": "Physics of Plasmas, vol. 13, no. 12, pp. 122101-1-10", "authors": ["Aanesland A", "Lieberman M", "Christine Charles"]}, {"title": "Comparison of stress in single and multiple layer depositions of plasma-deposited amorphous silicon dioxide", "year": "2006", "source": "Journal of Physics D: Applied Physics, vol. 39, pp. 164-171", "authors": ["Au V", "Christine Charles", "Boswell R"]}, {"title": "theory for formation of a low pressure, current-free double layer", "year": "2006", "source": "Journal of Physics D: Applied Physics, vol. 39, no. 15, pp. 3294-3304", "authors": ["Lieberman M", "Christine Charles", "Boswell R"]}, {"title": "Ion Detachment in the Helicon Double-Layer Thruster Exhaust Beam", "year": "2006", "source": "Journal of Propulsion and Power, vol. 22, no. 1, pp. 24-30", "authors": ["Gesto F", "Blackwell B", "Christine Charles"]}, {"title": "Solid Polymer Fuel Cell synthesis by low pressure plasmas: A short review", "year": "2006", "source": "European Physical Journal - Applied Physics, vol. 34, pp. 151-156", "authors": ["Brault P", "Roualdes S", "Caillard A", "Christine Charles"]}, {"title": "Deposition and diffusion of platinum nanoparticles in porous carbon assisted by plasma sputtering", "year": "2005", "source": "Surface and Coatings Technology, vol. 200, pp. 391-394", "authors": ["Caillard A", "Brault P", "Mathias J", "Christine Charles"]}, {"title": "Optical Losses in Silica Rib Waveguides Deposited by HARE-PECVD on Silicon Substrate", "year": "2005", "source": "Australian Conference on Optical Fibre Technology (ACOFT 2005), ed. Conference Program Committee, Optical Society of America, Australia, pp. 303-305", "authors": ["Bulla D", "Li W", "Christine Charles"]}, {"title": "Reduction of the Sidewall Roughness of Silica Optical Waveguides", "year": "2005", "source": "Australian Conference on Optical Fibre Technology (ACOFT 2005), ed. Conference Program Committee, Optical Society of America, Australia, pp. 472-474", "authors": ["Li W", "Bulla D", "Love J", "Christine Charles"]}, {"title": "Deposition and Diffusion of Platinum Nanoparticles in Porous Carbon Assisted by Plasma Sputtering", "year": "2005", "source": "Surface and Coatings Technology, vol. 200, no. 1-4, pp. 391-394", "authors": ["Caillard A", "Brault P", "Mathias J", "Christine Charles"]}, {"title": "Fluctuation in a Helicon Plasma with Additional Immersed Antenna", "year": "2005", "source": "IEEE Transactions on Plasma Science, vol. 33, no. 2, pp. 360-361", "authors": ["Aanesland A", "Christine Charles", "Boswell R"]}, {"title": "One-dimensional Particle-in-cell Simulation of a Current-free Double-layer in an Expanding Plasma", "year": "2005", "source": "Physics of Plasmas, vol. 12, no. 5, pp. 052317-1-10", "authors": ["Meige A", "Boswell R", "Christine Charles"]}, {"title": "Spatially Resolved Energy Analyzer Measurements of an Ion Beam on the Low Potential Side of a Current-free Double-layer", "year": "2005", "source": "IEEE Transactions on Plasma Science, vol. 33, no. 2, pp. 336-337", "authors": ["Christine Charles"]}, {"title": "High Source Potential Upstream of a Current-free Electric Double-layer", "year": "2005", "source": "Physics of Plasmas, vol. 12, no. 4, pp. 044508-1-4", "authors": ["Christine Charles"]}, {"title": "One-dimensional Simulation of an Ion Beam Generated by a Current-free Double-layer", "year": "2005", "source": "IEEE Transactions on Plasma Science, vol. 33, no. 2, pp. 334-335", "authors": ["Meige A", "Boswell R", "Christine Charles"]}, {"title": "Low-loss Silica-based Optical Film Waveguides Deposited by Helicon-activated Reactive Evaporation", "year": "2005", "source": "Journal of Lightwave Technology, vol. 23, no. 3, pp. 1302-1307", "authors": ["Bulla D", "Li W", "Christine Charles"]}, {"title": "Thickness-dependent Stress in Plasma-deposited Silicon Dioxide Films", "year": "2005", "source": "Journal of Applied Physics, vol. 97, no. 8, pp. 084912-1-7", "authors": ["Au V", "Christine Charles", "Bulla D"]}, {"title": "Deep Dry-etch of Silica in a Helicon Plasma Etcher for Optical Waveguide Fabrication", "year": "2005", "source": "Journal of Vacuum Science and Technology A, vol. 23, no. 1, pp. 146-150", "authors": ["Li W", "Bulla D", "Love J", "Christine Charles"]}, {"title": "Micro-arcing instability in RF PECVD plasma system", "year": "2005", "source": "Surface and Coatings Technology, vol. 198, pp. 379-383", "authors": ["Yin Y", "Bilek M", "McKenzie D", "Christine Charles"]}, {"title": "The ion velocity distribution function in a current-free double layer", "year": "2005", "source": "Physics of Plasmas, vol. 12, no. 093502, pp. 1-7", "authors": ["Keesee A", "Scime E", "Christine Charles"]}, {"title": "Grounded Radio-frequency Electrodes in Contact with High Density Plasmas", "year": "2005", "source": "Physics of Plasmas, vol. 12, no. 103505, pp. 1-7", "authors": ["Aanesland A", "Christine Charles", "Boswell R"]}, {"title": "The effect of phase difference between powered electrodes on RF plasmas", "year": "2005", "source": "Plasma Sources Science and Technology, vol. 14, pp. 407-411", "authors": ["Proschek M", "Yin Y", "Christine Charles"]}, {"title": "Experimental evidence of a double layer in a large volume helicon reactor", "year": "2005", "source": "Physical Review Letters, vol. 95, no. 205002, pp. 1-4", "authors": ["Sutherland O", "Christine Charles", "Plihon N"]}, {"title": "comparison between experimental results and a fluid description of a low pressure discharge driven by a double-saddle antenna", "year": "2005", "source": "Journal of Physics D: Applied Physics, vol. 38, pp. 2825-2829", "authors": ["Yoon Y", "Christine Charles", "Boswell R"]}, {"title": "Observations of ion-beam formation in a current-free doublelayer", "year": "2005", "source": "Physical Review Letters, vol. 95, no. 025004, pp. 1-4", "authors": ["Sun X", "Keesee A", "Biloiu C", "Christine Charles"]}, {"title": "Deposition and Characterization of Silica-Based Films by Helicon-Activated Reactive Evaporation Applied to Optical Waveguide Fabrication", "year": "2004", "source": "Applied Optics, vol. 43, no. 14, pp. 2978-2985", "authors": ["Bulla D", "Li W", "Christine Charles"]}, {"title": "Hydrogen ion beam generated by a current-free double layer in a helicon plasma", "year": "2004", "source": "Applied Physics Letters, vol. 84, no. 3, pp. 332-4", "authors": ["Christine Charles"]}, {"title": "Micro-arcing instability in radio frequency plasmas", "year": "2004", "source": "Journal of Physics D: Applied Physics, vol. 37, pp. 2871-2875", "authors": ["Yin Y", "Bilek M", "McKenzie D", "Christine Charles"]}, {"title": "Laboratory evidence of a supersonic ion beam generated by a current-free helicon double-layer", "year": "2004", "source": "Physics of Plasmas, vol. 11, no. 4, pp. 1706-14", "authors": ["Christine Charles", "Boswell R"]}, {"title": "Experimental evidence of parametric decay processes in the variable specific impulse magnetoplasma rocket (VASIMR) helicon plasma source", "year": "2004", "source": "Physics of Plasmas, vol. 11, no. 11, pp. 5125-9", "authors": ["Boswell R", "Sutherland O", "Christine Charles"]}, {"title": "Helicon plasma with additional immersed antenna", "year": "2004", "source": "Journal of Physics D: Applied Physics, vol. 37, no. 9, pp. 1334-41", "authors": ["Aanesland A", "Christine Charles", "Boswell R"]}, {"title": "OH Absorption Peak on Silica Planar Waveguide Deposited by HARE-PECVD", "year": "2004", "source": "Australian Conference on Optical Fibre Technology (ACOFT 2004), ed. B. Eggleton, D. Sampson, S. Frisken, A. Mitchell, S. Jackson, A. Ankiewicz, M. S, IREE Society, Canberra, pp. ACOFT-PO4-1-3", "authors": ["Bulla D", "Li W", "Christine Charles"]}, {"title": "Dry Etching of SiO2 Thin Films for Optical Waveguide Fabrication", "year": "2004", "source": "Australian Conference on Optical Fibre Technology (ACOFT 2004), ed. B. Eggleton, D. Sampson, S. Frisken, A. Mitchell, S. Jackson, A. Ankiewicz, M. S, IREE Society, Canberra, pp. ACOFT-PO19-1-3", "authors": ["Li W", "Bulla D", "Love J", "Christine Charles"]}, {"title": "Time development of a current-free double-layer", "year": "2004", "source": "Physics of Plasmas, vol. 11, no. 8, pp. 3808-3812", "authors": ["Christine Charles", "Boswell R"]}, {"title": "Plasma sputtering deposition of platinum into porous fuel cell electrodes", "year": "2004", "source": "Journal of Physics D: Applied Physics, vol. 37, pp. 3419-23", "authors": ["Brault P", "Caillard A", "Thomann A", "Christine Charles"]}, {"title": "Breakdown Behavior in Radio-frequency Argon Discharges", "year": "2003", "source": "Physics of Plasmas, vol. 10, no. 3, pp. 875-881", "authors": ["Smith H", "Christine Charles", "Boswell R"]}, {"title": "Geometry Effects upon the Transmission Loss in Optical Rib Waveguides Fabricated using Chemical Etching", "year": "2003", "source": "COIN and Australian Conference on Optical Fibre Technology (COIN/ACOFT 2003), ed. T.A. Nirmalathas and J.W. Park, E A Books, Online, pp. 748-751", "authors": ["Bulla D", "Li W", "Christine Charles"]}, {"title": "Current-free Double-layer Formation in a High-density Helicon Discharge", "year": "2003", "source": "Applied Physics Letters, vol. 82, no. 9, pp. 1356-1358", "authors": ["Christine Charles", "Boswell R"]}, {"title": "Wall Effects on the Chemistry in a Pulsed Oxygen/Silane Radiofrequency Helicon Plasma", "year": "2003", "source": "Journal of Physics D: Applied Physics, vol. 36, pp. 2076-2082", "authors": ["Christine Charles"]}, {"title": "Energy Balance in a Low Pressure Capacitive Discharge Driven by a Double-saddle Antenna", "year": "2003", "source": "Physics of Plasmas, vol. 10, no. 3, pp. 891-899", "authors": ["Christine Charles", "Boswell R", "Lieberman M"]}, {"title": "Sputtering Effects in a Helicon Plasma with an Additional Immersed Antenna", "year": "2003", "source": "Plasma Sources Science and Technology, vol. 12, no. 1, pp. 85-88", "authors": ["Aanesland A", "Christine Charles", "Boswell R"]}, {"title": "Hydrogen Contamination in Ge-doped SiO2 Thin Films Prepared by Helicon Activated Reactive Evaporation", "year": "2003", "source": "Journal of Vacuum Science and Technology A, vol. 21, no. 3, pp. 792-796", "authors": ["Li W", "Bulla D", "Love J", "Christine Charles"]}, {"title": "Ge-Doped Silica Optical Waveguide Fabrication by HARE-PED", "year": "2002", "source": "Australian Conference on Optical Fibre Technology (ACOFT 2002), ed. J. Canning, Australian Institute of Physics, Sydney, pp. 50-52", "authors": ["Bulla D", "Li W", "Luther-Davies B", "Christine Charles"]}, {"title": "Reactive Evaporated Ge-SiO2 Thin Films for Planar Waveguide Application", "year": "2002", "source": "Australian Conference on Optical Fibre Technology (ACOFT 2002), ed. J. Canning, Australian Institute of Physics, Sydney, pp. 68-71", "authors": ["Li W", "Bulla D", "Christine Charles"]}, {"title": "Stress and Mode Characterisation of Helicon Activated Reactive Evaporation Films and Rib Waveguides", "year": "2002", "source": "Australian Conference on Optical Fibre Technology (ACOFT 2002), ed. J. Canning, Australian Institute of Physics, Sydney, pp. 15-18", "authors": ["Au V", "Love J", "Christine Charles"]}, {"title": "Ge-doped SiO2 Thin Films Produced by Helicon Activated Reactive Evaporation", "year": "2002", "source": "Thin Solid Films, vol. 419, no. N1-2, pp. 82-87", "authors": ["Li W", "Bulla D", "Christine Charles"]}, {"title": "Effects of Cross Field Diffusion in a Low Pressure High Density Oxygen/Silane Plasma", "year": "2002", "source": "Journal of Vacuum Science and Technology A, vol. 20, no. 4, pp. 1275-1283", "authors": ["Christine Charles"]}, {"title": "Role of Ions in SiO2 Deposition with Pulsed and Continuous Helicon Plasmas", "year": "2002", "source": "Pure and Applied Chemistry, vol. 74, no. 3, pp. 401-405", "authors": ["Christine Charles"]}, {"title": "Plasma Synthesis of Catalytic Thin Films", "year": "2002", "source": "Pure and Applied Chemistry, vol. 74, no. 3, pp. 471-474", "authors": ["Thomann A", "Rozenbaum J", "Brault P", "Christine Charles"]}, {"title": "Growth of supported metallic ultrathin films deposited by plasma sputtering", "year": "2000", "source": "Journal of Vacuum Science and Technology A, vol. 2, no. 2000, pp. 35-57", "authors": ["Brault P", "Thomann A", "Rozenbaum J", "Christine Charles"]}, {"title": "Electrical characterization of a dc secondary discharge created during plasma sputtering deposition of palladium thin films", "year": "2000", "source": "Plasma Sources Science and Technology, vol. 9, no. 2000, pp. 176-182", "authors": ["Thomann A", "Christine Charles", "Cherradi N"]}, {"title": "bsolute measurements and modeling of radio frequency electric fields using a retarding field energy analyzer", "year": "2000", "source": "Physics of Plasmas, vol. 7, no. 12, pp. 5232-5241", "authors": ["Christine Charles", "Degeling A", "Sheridan T"]}, {"title": "Overview of Probe Diagnostics on the H-1 Heliac", "year": "1999", "source": "Review of Scientific Instruments, vol. 70, no. 1, pp. 476-479", "authors": ["Rudakov D", "Shats M", "Boswell R", "Christine Charles"]}]}, "Microsoft-Academic": [{"title": "plasmas for spacecraft propulsion", "year": 2009, "source": "journal of physics d", "authors": [{"name": "christine charles", "affiliation": "australian national university"}], "id": 111927887}, {"title": "space micropropulsion systems for cubesats and small satellites from proximate targets to furthermost frontiers", "year": 2018, "source": "applied physics reviews", "authors": [{"name": "igor levchenko", "affiliation": "queensland university of technology"}, {"name": "igor levchenko", "affiliation": "nanyang technological university"}, {"name": "kateryna bazaka", "affiliation": "queensland university of technology"}, {"name": "yongjie ding", "affiliation": "harbin institute of technology"}, {"name": "yevgeny raitses", "affiliation": "princeton plasma physics laboratory"}, {"name": "stephane mazouffre", "affiliation": "university of orleans"}, {"name": "torsten henning", "affiliation": "university of giessen"}, {"name": "peter j klar", "affiliation": "university of giessen"}, {"name": "shunjiro shinohara", "affiliation": "tokyo university of agriculture and technology"}, {"name": "j schein", "affiliation": "bundeswehr university munich"}, {"name": "l garrigues", "affiliation": "university of toulouse"}, {"name": "minkwan kim", "affiliation": "university of southampton"}, {"name": "dan r lev", "affiliation": "rafael advanced defense systems"}, {"name": "f taccogna"}, {"name": "rod boswell", "affiliation": "australian national university"}, {"name": "christine charles", "affiliation": "australian national university"}, {"name": "hiroyuki koizumi", "affiliation": "university of tokyo"}, {"name": "yan shen", "affiliation": "china aerospace science and technology corporation"}, {"name": "carsten scharlemann", "affiliation": "university of applied sciences wiener neustadt"}, {"name": "michael keidar", "affiliation": "george washington university"}, {"name": "s xu", "affiliation": "nanyang technological university"}], "id": 2764457777}, {"title": "a review of recent laboratory double layer experiments", "year": 2007, "source": "plasma sources science and technology", "authors": [{"name": "christine charles", "affiliation": "australian national university"}], "id": 57082650}, {"title": "current free double layer formation in a high density helicon discharge", "year": 2003, "source": "applied physics letters", "authors": [{"name": "christine charles"}, {"name": "rod boswell"}], "id": 105243760}, {"title": "direct thrust measurement of a permanent magnet helicon double layer thruster", "year": 2011, "source": "applied physics letters", "authors": [{"name": "kazunori takahashi"}, {"name": "trevor lafleur"}, {"name": "christine charles"}, {"name": "peter alexander"}, {"name": "roderick boswell"}, {"name": "m perren"}, {"name": "robert laine"}, {"name": "sabrina pottinger"}, {"name": "vaios lappas"}, {"name": "t harle"}, {"name": "d lamprou"}], "id": 105243760}, {"title": "laboratory evidence of a supersonic ion beam generated by a current free helicon double layer", "year": 2004, "source": "physics of plasmas", "authors": [{"name": "christine charles"}, {"name": "roderick boswell"}], "id": 66354037}, {"title": "performance characterization of a helicon double layer thruster using direct thrust measurements", "year": 2011, "source": "journal of physics d", "authors": [{"name": "sabrina pottinger", "affiliation": "university of surrey"}, {"name": "viaos lappas", "affiliation": "university of surrey"}, {"name": "christine charles", "affiliation": "australian national university"}, {"name": "roderick boswell", "affiliation": "australian national university"}], "id": 111927887}, {"title": "observations of ion beam formation in a current free double layer", "year": 2005, "source": "physical review letters", "authors": [{"name": "xuan sun", "affiliation": "west virginia university"}, {"name": "a m keesee", "affiliation": "west virginia university"}, {"name": "costel biloiu", "affiliation": "west virginia university"}, {"name": "earl scime", "affiliation": "west virginia university"}, {"name": "albert meige", "affiliation": "australian national university"}, {"name": "christine charles", "affiliation": "australian national university"}, {"name": "roderick boswell", "affiliation": "australian national university"}], "id": 24807848}, {"title": "structurally supportive rf power inverter for a cubesat electrothermal plasma micro thruster with pcb inductors", "year": 2017, "source": "", "authors": [{"name": "wei liang", "affiliation": "stanford university"}, {"name": "luke raymond", "affiliation": "stanford university"}, {"name": "juan rivas davila", "affiliation": "stanford university"}, {"name": "christine charles", "affiliation": "australian national university"}, {"name": "roderick boswell", "affiliation": "australian national university"}]}, {"title": "xenon ion beam characterization in a helicon double layer thruster", "year": 2006, "source": "applied physics letters", "authors": [{"name": "christine charles"}, {"name": "roderick boswell"}, {"name": "m a lieberman"}], "id": 105243760}], "ANDS-Grants": [{"description": "Electric propulsion is the new wave of attitude control for spacecraft. Space engines must be small, lightweight and able to run unattended for over 20 years in a very harsh environment. The physics of a new electrothermal radiofrequency plasma thruster will be investigated. Neutral gas heating will be initially quantified by optical spectroscopy combined with computer generated simulated spectra. A space ready prototype will be designed, manufactured and developed to carry out direct measurements of thrust and gas heating in our large space simulation vacuum facility.", "title": "Discovery Projects - Grant ID: DP140100571", "id": "518060", "institutions": ["Australian National University"], "key": "http://purl.org/au-research/grants/arc/DP140100571", "researchers": ["Prof Dr Christine Charles"], "status": "closed", "fundingAmount": 391000, "fundingScheme": "Discovery Projects", "startDate": 2014, "endDate": 2016, "dateTimeModified": "2016-05-29T08:51:17Z", "dateTimeCreated": "2015-04-12T05:07:17Z", "funder": ["Australian Research Council"], "managingInstitution": ["Australian National University"], "principalInvestigator": null, "purl": "http://purl.org/au-research/grants/arc/DP140100571", "identifiers": ["http://purl.org/au-research/grants/arc/DP140100571", "DP140100571"], "subjects": ["ATOMIC, MOLECULAR, NUCLEAR, PARTICLE AND PLASMA PHYSICS", "PHYSICAL SCIENCES", "plasmas", "space", "thruster"], "links": [{"rel": "self", "href": "http://researchdata.edu.au/api/v2.0/registry/activities/grants/518060"}]}, {"description": "This project aims to develop the prerequisite knowledge to underpin new plasma technologies. Specifically, the project plans to provide new insight into the interaction between ionised gas plasma jets and biological soft tissue. It plans to use advanced analytical techniques and modelling simulations to investigate the physics of the plasma jet and processes occurring at the jet&ndash;tissue interface. It also plans to use (bio)engineered tissue targets, chemical, biological and cellular assays to probe the transport and effects of plasma reactive species deep within tissue. This new knowledge would enable the development of new plasma sources and protocols for applications in health, medicine, biotechnology and manufacturing.", "title": "Discovery Projects - Grant ID: DP160104298", "id": "664283", "institutions": ["University of South Australia"], "key": "http://purl.org/au-research/grants/arc/DP160104298", "researchers": ["Prof Robert Short", "Prof Dr Christine Charles", "Prof Roderick Boswell", "Prof Allison Cowin", "Dr Endre Szili", "Prof James Bradley", "Prof David Graves"], "status": "active", "fundingAmount": 336000, "fundingScheme": "Discovery Projects", "startDate": 2016, "endDate": 2020, "dateTimeModified": "2018-10-02T04:21:39Z", "dateTimeCreated": "1970-01-01T00:00:00Z", "funder": ["Australian Research Council"], "managingInstitution": ["University of South Australia"], "principalInvestigator": null, "purl": "http://purl.org/au-research/grants/arc/DP160104298", "identifiers": ["http://purl.org/au-research/grants/arc/DP160104298", "DP160104298"], "subjects": ["MANUFACTURING ENGINEERING", "ENGINEERING"], "links": [{"rel": "self", "href": "http://researchdata.edu.au/api/v2.0/registry/activities/grants/664283"}]}]}