{"ANU": {"name": "Huong Le Thu", "link": "https://researchers.anu.edu.au/researchers/le-thu-h", "colleges": "College of Asia & the Pacific", "email": "", "phone": "", "expertise": [], "interest": [], "biography": "", "project": [], "publication": []}, "Microsoft-Academic": [{"title": "china s dual strategy of coercion and inducementtowards asean", "year": 2019, "source": "pacific review", "authors": [{"name": "huong le thu", "affiliation": "australian national university"}], "id": 136982956}, {"title": "evaluating the cultural cooperation the role of the asia europe foundation asef in the asia europe meeting asem process", "year": 2014, "source": "asia europe journal", "authors": [{"name": "huong le thu"}], "id": 72124352}, {"title": "vietnam and the search for security leadership in asean", "year": 2021, "source": "asian security", "authors": [{"name": "ralf emmers"}, {"name": "huong le thu"}], "id": 146934403}, {"title": "asean 50 southeast asia risk what should be done", "year": 2018, "source": "", "authors": [{"name": "shiro armstrong"}, {"name": "niruban balachandran"}, {"name": "john blaxland"}, {"name": "ja ian chong"}, {"name": "daniel wei boon chua"}, {"name": "karl eikenberry"}, {"name": "ralf emmers"}, {"name": "donald k emmerson"}, {"name": "lori forman"}, {"name": "bates gill"}, {"name": "james hartsell"}, {"name": "richard javad heydarian"}, {"name": "james hirai"}, {"name": "yoichi kato"}, {"name": "evan laksmana"}, {"name": "justin nankivell"}, {"name": "kerry lynn nankivell"}, {"name": "kaewkamol pitakdumrongkit"}, {"name": "greg poling"}, {"name": "greg raymond"}, {"name": "tan see seng"}, {"name": "huong le thu"}, {"name": "barbara weisel"}, {"name": "belinda a yeomans"}]}, {"title": "many faces and one identity asean in the case of human rights regime", "year": 2010, "source": "", "authors": [{"name": "huong le thu"}]}, {"title": "the quadrilateral security dialogue and asean centrality", "year": 2020, "source": "", "authors": [{"name": "huong le thu"}]}, {"title": "vietnam s persistent foreign policy dilemma caught between self reliance and proactive integration", "year": 2018, "source": "asia policy", "authors": [{"name": "huong le thu"}], "id": 2764671667}, {"title": "southeast asian regional cooperation and combating human trafficking", "year": 2018, "source": "", "authors": [{"name": "huong le thu"}]}, {"title": "the value added asem the socio cultural dialogue", "year": 2018, "source": "", "authors": [{"name": "huong le thu"}]}, {"title": "indo pacific election pulse 2019 thailand indonesia india and australia", "year": 2019, "source": "", "authors": [{"name": "huong le thu"}]}], "ANDS-Grants": []}