{"ANU": {"name": "Lorenzo Dalla Corte", "link": "https://researchers.anu.edu.au/researchers/dalla-corte-l", "colleges": "ANU College of Law", "email": "Lorenzo.DallaCorte@anu.edu.au", "phone": "", "expertise": [], "interest": [], "biography": "", "project": [], "publication": []}, "Microsoft-Academic": [{"title": "a data protection impact assessment methodology for cloud", "year": 2015, "source": "", "authors": [{"name": "rehab alnemr", "affiliation": "hewlett packard"}, {"name": "erdal cayirci", "affiliation": "university of stavanger"}, {"name": "lorenzo dalla corte", "affiliation": "tilburg university"}, {"name": "alexandr garaga"}, {"name": "ronald leenes", "affiliation": "tilburg university"}, {"name": "rodney mhungu", "affiliation": "tilburg university"}, {"name": "siani pearson", "affiliation": "hewlett packard"}, {"name": "chris reed", "affiliation": "queen mary university of london"}, {"name": "anderson santana de oliveira"}, {"name": "dimitra stefanatou", "affiliation": "tilburg university"}, {"name": "katerina tetrimida", "affiliation": "tilburg university"}, {"name": "asma vranaki", "affiliation": "queen mary university of london"}]}, {"title": "open data exposed", "year": 2018, "source": "", "authors": [{"name": "bastiaan van loenen", "affiliation": "delft university of technology"}, {"name": "glenn vancauwenberghe", "affiliation": "delft university of technology"}, {"name": "joep crompvoets", "affiliation": "katholieke universiteit leuven"}, {"name": "lorenzo dalla corte", "affiliation": "delft university of technology"}, {"name": "lorenzo dalla corte", "affiliation": "tilburg university"}]}, {"title": "personal data protection as a nonfunctional requirement in the smart city s development", "year": 2017, "source": "", "authors": [{"name": "lorenzo dalla corte"}, {"name": "bastiaan van loenen", "affiliation": "delft university of technology"}, {"name": "c m k c cuijpers"}]}, {"title": "personal data protection as a nonfunctional requirement in the smart city s development", "year": 2017, "source": "social science research network", "authors": [{"name": "lorenzo dalla corte", "affiliation": "delft university of technology"}, {"name": "lorenzo dalla corte", "affiliation": "tilburg university"}, {"name": "bastiaan van loenen", "affiliation": "delft university of technology"}, {"name": "c m k c cuijpers", "affiliation": "tilburg university"}], "id": 2751751161}, {"title": "d c 6 2 prototype for the data protection impact assessment tool", "year": 2014, "source": "", "authors": [{"name": "alexandr garaga"}, {"name": "anderson santana de oliveira"}, {"name": "erdal cayirci"}, {"name": "lorenzo dalla corte"}, {"name": "ronald leenes"}, {"name": "rodney mhungu"}, {"name": "dimitra stefanatou"}, {"name": "katerina tetrimida"}, {"name": "rehab alnemr"}, {"name": "massimo felici"}, {"name": "siani pearson"}, {"name": "asma vranaki"}]}, {"title": "scoping personal data towards a nuanced interpretation of the material scope of eu data protecton law", "year": 2019, "source": "european journal of law and technology", "authors": [{"name": "lorenzo dalla corte", "affiliation": "delft university of technology"}], "id": 2764792111}, {"title": "the european right to data protection in relation to open data", "year": 2018, "source": "", "authors": [{"name": "lorenzo dalla corte", "affiliation": "delft university of technology"}, {"name": "lorenzo dalla corte", "affiliation": "tilburg university"}]}, {"title": "towards open data across the pond", "year": 2018, "source": "", "authors": [{"name": "lorenzo dalla corte", "affiliation": "delft university of technology"}]}, {"title": "the governance of cybersecurity a comparative quick scan of approaches in canada estonia germany the netherlands and the uk", "year": 2015, "source": "", "authors": [{"name": "samantha adams"}, {"name": "marlou brokx"}, {"name": "lorenzo dalla corte"}, {"name": "masa galic"}, {"name": "kaspar kala"}, {"name": "bertjaap koops"}, {"name": "ronald leenes"}, {"name": "m h m schellekens"}, {"name": "karine e silva"}, {"name": "ivan skorvanek"}]}, {"title": "a right to a rule on the substance and essence of the fundamental right to personal data protection", "year": 2020, "source": "", "authors": [{"name": "lorenzo dalla corte"}]}], "ANDS-Grants": []}