{"ANU": {"name": "Martha Kinsman", "link": "https://researchers.anu.edu.au/researchers/kinsman-m", "colleges": "College of Arts and Social Sciences", "email": "martha.kinsman@anu.edu.au", "phone": "", "expertise": [], "interest": [], "biography": "", "project": [], "publication": []}, "Microsoft-Academic": [{"title": "different but equal the rise and demise of the tafe teachers association of australia 1964 1992", "year": 2019, "source": "", "authors": [{"name": "martha kinsman"}]}], "ANDS-Grants": []}