{"ANU": {"name": "Raglan Maddox", "link": "https://researchers.anu.edu.au/researchers/maddox-r", "colleges": "College of Health & Medicine", "email": "Raglan.Maddox@anu.edu.au", "phone": "", "expertise": ["Public Health And Health Services", "Other Medical And Health Sciences"], "interest": ["Commercial tobacco useTobacco programs and policiesLongitudinal cohort studiesSocial EpidemiologySocial determinants of health and wellbeing"], "biography": "", "project": [], "publication": [{"title": "Tobacco smoking and mortality among Aboriginal and Torres Strait Islander adults in Australia", "year": "2021", "source": "International Journal of Epidemiology, vol. Online", "authors": ["Thurber K", "Banks E", "Joshy G", "Raglan Maddox"]}, {"title": "Lessons for the global primary care response to COVID-19: a rapid review of evidence from past epidemics", "year": "2021", "source": "Family Practice, pp. 1-15", "authors": ["Desborough J", "Hall S", "Phillips C", "Raglan Maddox"]}, {"title": "Review of tobacco use among Aboriginal and Torres Strait Islander peoples", "year": "2020", "source": "Australian Indigenous Health Bulletin, vol. 20, no. 2, pp. 1-62", "authors": ["Colonna E", "Raglan Maddox", "Cohen R"]}]}, "Microsoft-Academic": [{"title": "foundation for a smoke free world and healthy indigenous futures an oxymoron", "year": 2019, "source": "tobacco control", "authors": [{"name": "andrew waa", "affiliation": "university of otago"}, {"name": "bridget robson", "affiliation": "university of otago"}, {"name": "heather gifford"}, {"name": "janet smylie"}, {"name": "jeff reading", "affiliation": "st paul s hospital"}, {"name": "jeffrey a henderson"}, {"name": "patricia nez henderson"}, {"name": "raglan maddox"}, {"name": "raymond lovett", "affiliation": "australian national university"}, {"name": "sandra eades", "affiliation": "university of melbourne"}, {"name": "summer may finlay"}, {"name": "tom calma"}], "id": 149729710}, {"title": "unmet health needs and discrimination by healthcare providers among an indigenous population in toronto canada", "year": 2020, "source": "canadian journal of public health revue canadienne de sante publique", "authors": [{"name": "george tjensvoll kitching", "affiliation": "university of western ontario"}, {"name": "george tjensvoll kitching", "affiliation": "norwegian university of science and technology"}, {"name": "michelle firestone", "affiliation": "university of toronto"}, {"name": "michelle firestone", "affiliation": "st michael s hospital"}, {"name": "berit schei", "affiliation": "norwegian university of science and technology"}, {"name": "sara wolfe"}, {"name": "cheryllee bourgeois"}, {"name": "patricia ocampo", "affiliation": "university of toronto"}, {"name": "patricia ocampo", "affiliation": "st michael s hospital"}, {"name": "michael rotondi", "affiliation": "york university"}, {"name": "rosane nisenbaum", "affiliation": "university of toronto"}, {"name": "rosane nisenbaum", "affiliation": "st michael s hospital"}, {"name": "raglan maddox", "affiliation": "university of canberra"}, {"name": "raglan maddox", "affiliation": "st michael s hospital"}, {"name": "janet smylie", "affiliation": "university of toronto"}, {"name": "janet smylie", "affiliation": "st michael s hospital"}], "id": 73868107}, {"title": "evidence for a comprehensive approach to aboriginal tobacco control to maintain the decline in smoking an overview of reviews among indigenous peoples", "year": 2017, "source": "systematic reviews", "authors": [{"name": "catherine chamberlain"}, {"name": "susan perlen", "affiliation": "baker idi heart and diabetes institute"}, {"name": "susan perlen", "affiliation": "royal children s hospital"}, {"name": "sue e brennan", "affiliation": "monash university"}, {"name": "lucie rychetnik", "affiliation": "university of notre dame australia"}, {"name": "david p thomas"}, {"name": "raglan maddox", "affiliation": "cancer epidemiology unit"}, {"name": "raglan maddox", "affiliation": "university of canberra"}, {"name": "raglan maddox", "affiliation": "st michael s hospital"}, {"name": "noore alam", "affiliation": "queensland government"}, {"name": "emily banks", "affiliation": "australian national university"}, {"name": "andrew wilson", "affiliation": "university of sydney"}, {"name": "sandra eades", "affiliation": "monash university"}, {"name": "sandra eades", "affiliation": "baker idi heart and diabetes institute"}], "id": 82452678}, {"title": "effective knowledge translation approaches and practices in indigenous health research a systematic review protocol", "year": 2017, "source": "systematic reviews", "authors": [{"name": "melody e morton ninomiya", "affiliation": "st michael s hospital"}, {"name": "donna atkinson"}, {"name": "simon brascoupe", "affiliation": "carleton university"}, {"name": "michelle firestone", "affiliation": "university of toronto"}, {"name": "michelle firestone", "affiliation": "st michael s hospital"}, {"name": "nicole robinson", "affiliation": "canadian partnership against cancer"}, {"name": "jeff reading", "affiliation": "simon fraser university"}, {"name": "carolyn ziegler", "affiliation": "st michael s hospital"}, {"name": "raglan maddox", "affiliation": "university of canberra"}, {"name": "raglan maddox", "affiliation": "st michael s hospital"}, {"name": "janet smylie"}], "id": 82452678}, {"title": "still looking for mechanisms a realist review of batterer intervention programs", "year": 2020, "source": "trauma violence & abuse", "authors": [{"name": "alisa velonis", "affiliation": "university of illinois at chicago"}, {"name": "alisa velonis", "affiliation": "st michael s hospital"}, {"name": "debbie finn mahabir", "affiliation": "st michael s hospital"}, {"name": "raglan maddox", "affiliation": "st michael s hospital"}, {"name": "patricia ocampo", "affiliation": "university of toronto"}, {"name": "patricia ocampo", "affiliation": "st michael s hospital"}], "id": 170515770}, {"title": "identifying how to engage men in domestic violence research a concept mapping study", "year": 2019, "source": "journal of family violence", "authors": [{"name": "raglan maddox", "affiliation": "university of canberra"}, {"name": "raglan maddox", "affiliation": "st michael s hospital"}, {"name": "patricia ocampo", "affiliation": "university of toronto"}, {"name": "patricia ocampo", "affiliation": "st michael s hospital"}, {"name": "jonathan grove", "affiliation": "university of washington"}, {"name": "michael yonas"}, {"name": "carlos chan", "affiliation": "mcmaster university"}, {"name": "aly kassam", "affiliation": "st michael s hospital"}, {"name": "alisa velonis", "affiliation": "university of illinois at chicago"}, {"name": "alisa velonis", "affiliation": "st michael s hospital"}], "id": 53301456}, {"title": "asking the right questions screening men for partner violence", "year": 2021, "source": "journal of interpersonal violence", "authors": [{"name": "alisa velonis", "affiliation": "university of illinois at chicago"}, {"name": "alisa velonis", "affiliation": "st michael s hospital"}, {"name": "raglan maddox", "affiliation": "university of canberra"}, {"name": "raglan maddox", "affiliation": "st michael s hospital"}, {"name": "pearl buhariwala", "affiliation": "st michael s hospital"}, {"name": "janisha kamalanathan", "affiliation": "st michael s hospital"}, {"name": "maha awaiz hassan", "affiliation": "st michael s hospital"}, {"name": "tamam fadhil", "affiliation": "st michael s hospital"}, {"name": "patricia ocampo", "affiliation": "university of toronto"}, {"name": "patricia ocampo", "affiliation": "st michael s hospital"}], "id": 45333638}, {"title": "commercial tobacco and indigenous peoples a stock take on framework convention on tobacco control progress", "year": 2019, "source": "tobacco control", "authors": [{"name": "raglan maddox"}, {"name": "andrew waa", "affiliation": "university of otago"}, {"name": "kelley lee", "affiliation": "simon fraser university"}, {"name": "patricia nez henderson"}, {"name": "genevieve blais", "affiliation": "st michael s hospital"}, {"name": "jeff reading", "affiliation": "st paul s hospital"}, {"name": "raymond lovett", "affiliation": "australian national university"}], "id": 149729710}, {"title": "australian researchers oppose funding from the foundation for a smoke free world", "year": 2018, "source": "australian and new zealand journal of public health", "authors": [{"name": "david p thomas"}, {"name": "marita hefler"}, {"name": "billie bonevski", "affiliation": "university of newcastle"}, {"name": "tom calma", "affiliation": "university of canberra"}, {"name": "jonathan r carapetis", "affiliation": "university of western australia"}, {"name": "jonathan r carapetis", "affiliation": "boston children s hospital"}, {"name": "catherine chamberlain", "affiliation": "la trobe university"}, {"name": "simon chapman", "affiliation": "university of sydney"}, {"name": "mike daube", "affiliation": "university of western australia"}, {"name": "sandra eades", "affiliation": "university of melbourne"}, {"name": "summer may finlay", "affiliation": "university of south australia"}, {"name": "becky freeman", "affiliation": "university of sydney"}, {"name": "raymond lovett", "affiliation": "australian national university"}, {"name": "ross mackenzie", "affiliation": "macquarie university"}, {"name": "raglan maddox", "affiliation": "university of canberra"}, {"name": "melanie wakefield", "affiliation": "cancer council victoria"}], "id": 18972429}, {"title": "deadly progress changes in australian aboriginal and torres strait islander adult daily smoking 2004 2015", "year": 2017, "source": "public health research & practice", "authors": [{"name": "raymond lovett", "affiliation": "australian national university"}, {"name": "katherine a thurber", "affiliation": "australian national university"}, {"name": "alyson wright", "affiliation": "australian national university"}, {"name": "raglan maddox", "affiliation": "st michael s hospital"}, {"name": "emily banks", "affiliation": "australian national university"}], "id": 2738265844}], "ANDS-Grants": []}