{"ANU": {"name": "Syarifah Liza Munira", "link": "https://researchers.anu.edu.au/researchers/munira-sl", "colleges": "College of Health & Medicine", "email": "Liza.Munira@anu.edu.au", "phone": "", "expertise": [], "interest": ["Vaccine supplyImmunization programsPharmaceutical industryEconomic evaluationBehavioral economicsInnovative financing"], "biography": "Within her 20 years of experience working on policy and research at the national and international level, Liza\u2019s work in economics and global health has covered various issues such as public health systems, immunization, the pharmaceutical and vaccines industry, tobacco control, resource mobilization, innovative financing, poverty reduction, and decentralization.", "project": [], "publication": []}, "Microsoft-Academic": [{"title": "what influences government adoption of vaccines in developing countries a policy process analysis", "year": 2007, "source": "social science & medicine", "authors": [{"name": "syarifah liza munira", "affiliation": "the global fund to fight aids tuberculosis and malaria"}, {"name": "scott a fritzen", "affiliation": "national university of singapore"}], "id": 106822843}, {"title": "a cost analysis of producing vaccines in developing countries", "year": 2019, "source": "vaccine", "authors": [{"name": "syarifah liza munira", "affiliation": "university of indonesia"}, {"name": "j hendriks"}, {"name": "ines i atmosukarto"}, {"name": "martin friede", "affiliation": "world health organization"}, {"name": "louise m carter", "affiliation": "novartis"}, {"name": "james r g butler", "affiliation": "university of canberra"}, {"name": "archie c a clements", "affiliation": "curtin university"}], "id": 27359860}, {"title": "issues in selection of dtwp based combination vaccines", "year": 2003, "source": "vaccine", "authors": [{"name": "julie b milstien", "affiliation": "world health organization"}, {"name": "syarifah liza munira", "affiliation": "world health organization"}, {"name": "susan loretan mckinney"}], "id": 27359860}, {"title": "assessing hiv tb malaria and childhood immunization supply side readiness in indonesia", "year": 2018, "source": "", "authors": [{"name": "robert joseph magnani"}, {"name": "pandu harimurti"}, {"name": "eko setyo pambudi"}, {"name": "rachmat reksa samudra"}, {"name": "syarifah liza munira"}]}, {"title": "viability of local vaccine production in developing countries an economic analysis of cost structures revenue sizes market shares and vaccine prices", "year": 2017, "source": "", "authors": [{"name": "syarifah liza munira"}]}], "ANDS-Grants": []}