{"ANU": {"name": "Tim Maloney", "link": "https://researchers.anu.edu.au/researchers/maloney-tr", "colleges": "College of Asia & the Pacific", "email": "", "phone": "", "expertise": [], "interest": [], "biography": "", "project": [], "publication": []}, "Microsoft-Academic": [{"title": "stacked pmos clamps for high voltage power supply protection", "year": 2001, "source": "microelectronics reliability", "authors": [{"name": "tim maloney", "affiliation": "intel"}, {"name": "wilson kan", "affiliation": "intel"}], "id": 133646729}, {"title": "stacked pmos clamps for high voltage power supply protection", "year": 1999, "source": "", "authors": [{"name": "tim maloney", "affiliation": "intel"}, {"name": "wilson kan", "affiliation": "intel"}]}, {"title": "children in the public benefit system at risk of maltreatment identification via predictive modeling", "year": 2013, "source": "american journal of preventive medicine", "authors": [{"name": "rhema vaithianathan", "affiliation": "university of auckland"}, {"name": "tim maloney", "affiliation": "auckland university of technology"}, {"name": "emily putnamhornstein", "affiliation": "auckland university of technology"}, {"name": "nan jiang", "affiliation": "university of southern california"}], "id": 195759676}, {"title": "world s earliest ground edge axe production coincides with human colonisation of australia", "year": 2016, "source": "australian archaeology", "authors": [{"name": "peter hiscock", "affiliation": "university of sydney"}, {"name": "sue oconnor", "affiliation": "australian national university"}, {"name": "jane balme", "affiliation": "university of western australia"}, {"name": "tim maloney", "affiliation": "australian national university"}], "id": 105714911}, {"title": "using validated measures of high school academic achievement to predict university success", "year": 2019, "source": "", "authors": [{"name": "kamakshi singh", "affiliation": "auckland university of technology"}, {"name": "tim maloney", "affiliation": "auckland university of technology"}]}, {"title": "progress towards a joint esda jedec cdm standard methods experiments and results", "year": 2012, "source": "", "authors": [{"name": "alan righter", "affiliation": "analog devices"}, {"name": "terry welsher"}, {"name": "marti farris", "affiliation": "intel"}, {"name": "marty johnson", "affiliation": "texas instruments"}, {"name": "scott ward", "affiliation": "texas instruments"}, {"name": "marcel dekker"}, {"name": "tim maloney", "affiliation": "intel"}, {"name": "robert ashton", "affiliation": "on semiconductor"}, {"name": "leo g henry"}, {"name": "tom meuse", "affiliation": "thermo fisher scientific"}, {"name": "jon barth"}, {"name": "evan grund"}, {"name": "theo smedes", "affiliation": "nxp semiconductors"}, {"name": "paul ngan", "affiliation": "nxp semiconductors"}]}, {"title": "the fortified settlement of macapainara lautem district timor leste", "year": 2020, "source": "", "authors": [{"name": "sue oconnor", "affiliation": "australian national university"}, {"name": "david bulbeck", "affiliation": "australian national university"}, {"name": "noel amano", "affiliation": "max planck society"}, {"name": "philip piper", "affiliation": "australian national university"}, {"name": "sally brockwell"}, {"name": "andrew mcwilliam", "affiliation": "university of sydney"}, {"name": "jack n fenner", "affiliation": "australian national university"}, {"name": "jack oconnorveth", "affiliation": "australian national university"}, {"name": "rose whitau", "affiliation": "australian national university"}, {"name": "tim maloney", "affiliation": "griffith university"}, {"name": "michelle c langley", "affiliation": "griffith university"}, {"name": "mirani litster"}, {"name": "james lankton", "affiliation": "university college london"}, {"name": "bernard gratuze", "affiliation": "university of bordeaux"}, {"name": "william r dickinson", "affiliation": "university of arizona"}, {"name": "anthony barham", "affiliation": "australian national university"}, {"name": "richard c willan"}]}, {"title": "excavations at the site of vasino lautem district timor leste", "year": 2020, "source": "", "authors": [{"name": "sally brockwell"}, {"name": "sue oconnor", "affiliation": "australian national university"}, {"name": "jack n fenner", "affiliation": "australian national university"}, {"name": "andrew mcwilliam", "affiliation": "university of sydney"}, {"name": "noel amano", "affiliation": "max planck society"}, {"name": "philip piper", "affiliation": "australian national university"}, {"name": "david bulbeck", "affiliation": "australian national university"}, {"name": "mirani litster", "affiliation": "australian national university"}, {"name": "rose whitau", "affiliation": "australian national university"}, {"name": "jack oconnorveth", "affiliation": "australian national university"}, {"name": "tim maloney", "affiliation": "griffith university"}, {"name": "judith cameron", "affiliation": "australian national university"}, {"name": "richard c willan", "affiliation": "australian national university"}, {"name": "william r dickinson", "affiliation": "university of arizona"}]}, {"title": "black white differences in child maltreatment reports and foster care placements a statistical decomposition using linked administrative data", "year": 2017, "source": "maternal and child health journal", "authors": [{"name": "tim maloney", "affiliation": "auckland university of technology"}, {"name": "nan jiang", "affiliation": "auckland university of technology"}, {"name": "emily putnamhornstein", "affiliation": "university of southern california"}, {"name": "erin dalton", "affiliation": "allegheny county"}, {"name": "rhema vaithianathan", "affiliation": "auckland university of technology"}], "id": 96699677}, {"title": "carpenters gap 1 a 47 000 year old record of indigenous adaption and innovation", "year": 2018, "source": "quaternary science reviews", "authors": [{"name": "tim maloney", "affiliation": "australian national university"}, {"name": "sue oconnor", "affiliation": "australian national university"}, {"name": "rachel wood", "affiliation": "australian national university"}, {"name": "ken aplin", "affiliation": "australian national university"}, {"name": "jane balme", "affiliation": "university of western australia"}], "id": 81424476}], "ANDS-Grants": []}